stamox/__init__.py
stamox/basic.py
stamox/functions.py
stamox/pipe_functions.py
stamox/transformation.py
stamox/anova/__init__.py
stamox/anova/one_way/__init__.py
stamox/anova/one_way/_aov.py
stamox/cluster/__init__.py
stamox/cluster/_kmeans.py
stamox/core/__init__.py
stamox/core/_func_state.py
stamox/core/base.py
stamox/core/better_partial.py
stamox/core/jit.py
stamox/core/maps.py
stamox/core/pipe.py
stamox/correlation/__init__.py
stamox/correlation/_cor.py
stamox/correlation/_pearson.py
stamox/correlation/_spearman.py
stamox/decomposition/__init__.py
stamox/decomposition/_pca.py
stamox/distribution/__init__.py
stamox/distribution/_beta.py
stamox/distribution/_binomial.py
stamox/distribution/_cauchy.py
stamox/distribution/_chisq.py
stamox/distribution/_ecdf.py
stamox/distribution/_exp.py
stamox/distribution/_f.py
stamox/distribution/_gamma.py
stamox/distribution/_laplace.py
stamox/distribution/_normal.py
stamox/distribution/_pareto.py
stamox/distribution/_poisson.py
stamox/distribution/_t.py
stamox/distribution/_uniform.py
stamox/distribution/_utils.py
stamox/distribution/_weibull.py
stamox/experimental/__init__.py
stamox/experimental/maps/__init__.py
stamox/experimental/maps/auto_map.py
stamox/experimental/maps/cube_map.py
stamox/formula/__init__.py
stamox/formula/_formula.py
stamox/hypothesis/__init__.py
stamox/hypothesis/_bartlett.py
stamox/hypothesis/_base.py
stamox/hypothesis/_durbin_watson.py
stamox/hypothesis/_friedman.py
stamox/math/__init__.py
stamox/math/combination.py
stamox/math/special.py
stamox/regression/__init__.py
stamox/regression/_base.py
stamox/regression/_lm.py
stamox/sample/__init__.py
stamox/sample/_bootstrap.py
stamox/sample/_jackknife.py
stamox-0.1.5.dist-info/LICENCE
stamox-0.1.5.dist-info/METADATA
stamox-0.1.5.dist-info/WHEEL
stamox-0.1.5.dist-info/top_level.txt
stamox-0.1.5.dist-info/RECORD
