Metadata-Version: 2.1
Name: stamox
Version: 0.1.5
Summary: Accelerate Your Statistical Analysis with JAX.
Home-page: https://github.com/jiayaobo/stamox
Author: Jia Yaobo
License: Apache 2.0
Requires-Python: >=3.8
License-File: LICENCE
Requires-Dist: jax (>=0.4.6)
Requires-Dist: jaxtyping (>=0.2.14)
Requires-Dist: typing-extensions (>=4.5.0)
Requires-Dist: equinox (>=0.10.1)
Requires-Dist: jaxopt (>=0.6)
Requires-Dist: pandas (>=1.5.3)
Requires-Dist: patsy (>=0.5.3)
Requires-Dist: tensorflow-probability (>=0.19.0)
Requires-Dist: scipy
Provides-Extra: complete
Requires-Dist: jax (>=0.4.6) ; extra == 'complete'
Requires-Dist: jaxtyping (>=0.2.14) ; extra == 'complete'
Requires-Dist: typing-extensions (>=4.5.0) ; extra == 'complete'
Requires-Dist: equinox (>=0.10.1) ; extra == 'complete'
Requires-Dist: jaxopt (>=0.6) ; extra == 'complete'
Requires-Dist: pandas (>=1.5.3) ; extra == 'complete'
Requires-Dist: patsy (>=0.5.3) ; extra == 'complete'
Requires-Dist: tensorflow-probability (>=0.19.0) ; extra == 'complete'
Requires-Dist: scipy ; extra == 'complete'
Requires-Dist: pytest ; extra == 'complete'
Requires-Dist: numpy ; extra == 'complete'
Requires-Dist: sklearn ; extra == 'complete'
Requires-Dist: statsmodels ; extra == 'complete'
Requires-Dist: pandas ; extra == 'complete'
Provides-Extra: tests
Requires-Dist: pytest ; extra == 'tests'
Requires-Dist: scipy ; extra == 'tests'
Requires-Dist: numpy ; extra == 'tests'
Requires-Dist: sklearn ; extra == 'tests'
Requires-Dist: statsmodels ; extra == 'tests'
Requires-Dist: pandas ; extra == 'tests'
